[{
  "_id": {
    "$oid": "6770ac90314eefb30a21949f"
  },
  "name": "Ведение блога"
},
{
  "_id": {
    "$oid": "6770ac90314eefb30a2194a0"
  },
  "name": "Волонтёрство"
},
{
  "_id": {
    "$oid": "6770ac90314eefb30a2194a1"
  },
  "name": "Выращивание растений"
},
{
  "_id": {
    "$oid": "6770ac90314eefb30a2194a2"
  },
  "name": "Вышивание"
},
{
  "_id": {
    "$oid": "6770ac90314eefb30a2194a3"
  },
  "name": "Занятие боевыми искусствами"
},
{
  "_id": {
    "$oid": "6770ac90314eefb30a2194a4"
  },
  "name": "Занятие йогой"
},
{
  "_id": {
    "$oid": "6770ac90314eefb30a2194a5"
  },
  "name": "Занятие фитнесом"
},
{
  "_id": {
    "$oid": "6770ac90314eefb30a2194a6"
  },
  "name": "Игра в страйкбол"
},
{
  "_id": {
    "$oid": "6770ac90314eefb30a2194a7"
  },
  "name": "Игра в футбол"
},
{
  "_id": {
    "$oid": "6770ac90314eefb30a2194a8"
  },
  "name": "Игра на гитаре"
},
{
  "_id": {
    "$oid": "6770ac90314eefb30a2194a9"
  },
  "name": "Игра на пианино"
},
{
  "_id": {
    "$oid": "6770ac90314eefb30a2194aa"
  },
  "name": "Изучение языков"
},
{
  "_id": {
    "$oid": "6770ac90314eefb30a2194ab"
  },
  "name": "Коллекционирование монет"
},
{
  "_id": {
    "$oid": "6770ac90314eefb30a2194ac"
  },
  "name": "Кулинария"
},
{
  "_id": {
    "$oid": "6770ac90314eefb30a2194ad"
  },
  "name": "Лепка из глины"
},
{
  "_id": {
    "$oid": "6770ac90314eefb30a2194ae"
  },
  "name": "Метание копья"
},
{
  "_id": {
    "$oid": "6770ac90314eefb30a2194af"
  },
  "name": "Метание ножей"
},
{
  "_id": {
    "$oid": "6770ac90314eefb30a2194b0"
  },
  "name": "Охота"
},
{
  "_id": {
    "$oid": "6770ac90314eefb30a2194b1"
  },
  "name": "Пение"
},
{
  "_id": {
    "$oid": "6770ac90314eefb30a2194b2"
  },
  "name": "Пивоварение"
},
{
  "_id": {
    "$oid": "6770ac90314eefb30a2194b3"
  },
  "name": "Подводное плавание"
},
{
  "_id": {
    "$oid": "6770ac90314eefb30a2194b4"
  },
  "name": "Посещение концертов"
},
{
  "_id": {
    "$oid": "6770ac90314eefb30a2194b5"
  },
  "name": "Походы"
},
{
  "_id": {
    "$oid": "6770ac90314eefb30a2194b6"
  },
  "name": "Просмотр аниме"
},
{
  "_id": {
    "$oid": "6770ac90314eefb30a2194b7"
  },
  "name": "Прохождение компьютерных игр"
},
{
  "_id": {
    "$oid": "6770ac90314eefb30a2194b8"
  },
  "name": "Пчеловодство"
},
{
  "_id": {
    "$oid": "6770ac90314eefb30a2194b9"
  },
  "name": "Работа с металлом"
},
{
  "_id": {
    "$oid": "6770ac90314eefb30a2194ba"
  },
  "name": "Радиолюбительство"
},
{
  "_id": {
    "$oid": "6770ac90314eefb30a2194bb"
  },
  "name": "Резьба по дереву"
},
{
  "_id": {
    "$oid": "6770ac90314eefb30a2194bc"
  },
  "name": "Решение головоломок"
},
{
  "_id": {
    "$oid": "6770ac90314eefb30a2194bd"
  },
  "name": "Рисование"
},
{
  "_id": {
    "$oid": "6770ac90314eefb30a2194be"
  },
  "name": "Рыбалка"
},
{
  "_id": {
    "$oid": "6770ac90314eefb30a2194bf"
  },
  "name": "Сбор грибов"
},
{
  "_id": {
    "$oid": "6770ac90314eefb30a2194c0"
  },
  "name": "Скалолазание"
},
{
  "_id": {
    "$oid": "6770ac90314eefb30a2194c1"
  },
  "name": "Создание битбокса"
},
{
  "_id": {
    "$oid": "6770ac90314eefb30a2194c2"
  },
  "name": "Создание фигурок оригами"
},
{
  "_id": {
    "$oid": "6770ac90314eefb30a2194c3"
  },
  "name": "Создание фокусов"
},
{
  "_id": {
    "$oid": "6770ac90314eefb30a2194c4"
  },
  "name": "Сочинение рэпа"
},
{
  "_id": {
    "$oid": "6770ac90314eefb30a2194c5"
  },
  "name": "Стрельба из лука"
},
{
  "_id": {
    "$oid": "6770ac90314eefb30a2194c6"
  },
  "name": "Сурвивализм"
},
{
  "_id": {
    "$oid": "6770ac90314eefb30a2194c7"
  },
  "name": "Сёрфинг"
},
{
  "_id": {
    "$oid": "6770ac90314eefb30a2194c8"
  },
  "name": "Танцы"
},
{
  "_id": {
    "$oid": "6770ac90314eefb30a2194c9"
  },
  "name": "Туризм"
},
{
  "_id": {
    "$oid": "6770ac90314eefb30a2194ca"
  },
  "name": "Фехтование"
},
{
  "_id": {
    "$oid": "6770ac90314eefb30a2194cb"
  },
  "name": "Чтение"
},
{
  "_id": {
    "$oid": "6770ac90314eefb30a2194cc"
  },
  "name": "Шопинг"
},
{
  "_id": {
    "$oid": "6770ac90314eefb30a2194cd"
  },
  "name": "Игры с кошками"
},
{
  "_id": {
    "$oid": "6770ac90314eefb30a2194ce"
  },
  "name": "Ночные прогулки по городу"
},
{
  "_id": {
    "$oid": "6770ac90314eefb30a2194cf"
  },
  "name": "Сбор коллекции крышек от бутылок"
},
{
  "_id": {
    "$oid": "6770ac90314eefb30a2194d0"
  },
  "name": "Создание мемов"
},
{
  "_id": {
    "$oid": "6770ac90314eefb30a2194d1"
  },
  "name": "Дрессировка домашних животных"
},
{
  "_id": {
    "$oid": "6770ac90314eefb30a2194d2"
  },
  "name": "Самоделки и создание вещей из подручных материалов"
},
{
  "_id": {
    "$oid": "6770ac90314eefb30a2194d3"
  },
  "name": "Фотографирование своих ног"
},
{
  "_id": {
    "$oid": "6770ac90314eefb30a2194d4"
  },
  "name": "Ведущие вебкамеры (весёлые стримы)"
},
{
  "_id": {
    "$oid": "6770ac90314eefb30a2194d5"
  },
  "name": "Прокачка персонажей в видеоиграх"
},
{
  "_id": {
    "$oid": "6770ac90314eefb30a2194d6"
  },
  "name": "Устроить ночные «кинопоказы» с друзьями"
},
{
  "_id": {
    "$oid": "6770ac90314eefb30a2194d7"
  },
  "name": "Паркур (если не боишься падений)"
},
{
  "_id": {
    "$oid": "6770ac90314eefb30a2194d8"
  },
  "name": "Гонки на самокате или скейтборде"
},
{
  "_id": {
    "$oid": "6770ac90314eefb30a2194d9"
  },
  "name": "Изучение финансов и инвестирование"
},
{
  "_id": {
    "$oid": "6770ac90314eefb30a2194da"
  },
  "name": "Занятие астрономией"
},
{
  "_id": {
    "$oid": "6770ac90314eefb30a2194db"
  },
  "name": "Программирование"
},
{
  "_id": {
    "$oid": "6770ac90314eefb30a2194dc"
  },
  "name": "Ремонт и реставрация мебели"
},
{
  "_id": {
    "$oid": "6770ac90314eefb30a2194dd"
  },
  "name": "Саморазвитие и медитация"
},
{
  "_id": {
    "$oid": "6770ac90314eefb30a2194de"
  },
  "name": "Уход за кожей и волосами"
},
{
  "_id": {
    "$oid": "6770ac90314eefb30a2194df"
  },
  "name": "Экоактивизм и переработка материалов"
},
{
  "_id": {
    "$oid": "6770ac90314eefb30a2194e0"
  },
  "name": "Садоводство и создание органического сада"
},
{
  "_id": {
    "$oid": "6770ac90314eefb30a2194e1"
  },
  "name": "Киберспорт"
},
{
  "_id": {
    "$oid": "6770ac90314eefb30a2194e2"
  },
  "name": "Проектирование и моделирование"
},
{
  "_id": {
    "$oid": "6770ac90314eefb30a2194e3"
  },
  "name": "Флористика"
},
{
  "_id": {
    "$oid": "6770ac90314eefb30a2194e4"
  },
  "name": "Изучение психологии"
},
{
  "_id": {
    "$oid": "6770ac90314eefb30a2194e5"
  },
  "name": "Микросадоводство (выращивание овощей в квартире)"
}]